sealionconda/__init__.py
sealionconda/app.py
sealionconda/utils.py
sealion_conda-0.0.1.post2.dist-info/METADATA
sealion_conda-0.0.1.post2.dist-info/WHEEL
sealion_conda-0.0.1.post2.dist-info/entry_points.txt
sealion_conda-0.0.1.post2.dist-info/top_level.txt
sealion_conda-0.0.1.post2.dist-info/RECORD
