Metadata-Version: 2.1
Name: sealion-conda
Version: 0.0.1.post2
Summary: Sealion-Conda, Created by OpenSealion Organization, a tool to clone, pkg and create a conda environment between machines
Home-page: https://github.com/opensealion/sealion-conda
Author: arkmon
Author-email: 
License: Apache License 2.0
Keywords: sealion-conda,sealionconda,sc
Classifier: Development Status :: 3 - Alpha
Requires-Dist: tqdm
